{"schema":{"fields":[{"name":"date","type":"string"},{"name":"Ls","type":"number"}],"primaryKey":["date"],"pandas_version":"1.4.0"},"data":[{"date":"1880-Jan-01","Ls":357.8},{"date":"1880-Jul-01","Ls":359.0},{"date":"1881-Jan-01","Ls":0.1},{"date":"1881-Jul-01","Ls":1.2},{"date":"1882-Jan-01","Ls":2.3},{"date":"1882-Jul-01","Ls":3.4},{"date":"1883-Jan-01","Ls":4.5},{"date":"1883-Jul-01","Ls":5.6},{"date":"1884-Jan-01","Ls":6.8},{"date":"1884-Jul-01","Ls":7.9},{"date":"1885-Jan-01","Ls":9.0},{"date":"1885-Jul-01","Ls":10.1},{"date":"1886-Jan-01","Ls":11.2},{"date":"1886-Jul-01","Ls":12.3},{"date":"1887-Jan-01","Ls":13.4},{"date":"1887-Jul-01","Ls":14.5},{"date":"1888-Jan-01","Ls":15.6},{"date":"1888-Jul-01","Ls":16.7},{"date":"1889-Jan-01","Ls":17.8},{"date":"1889-Jul-01","Ls":18.9},{"date":"1890-Jan-01","Ls":20.1},{"date":"1890-Jul-01","Ls":21.2},{"date":"1891-Jan-01","Ls":22.3},{"date":"1891-Jul-01","Ls":23.4},{"date":"1892-Jan-01","Ls":24.5},{"date":"1892-Jul-01","Ls":25.6},{"date":"1893-Jan-01","Ls":26.7},{"date":"1893-Jul-01","Ls":27.8},{"date":"1894-Jan-01","Ls":28.9},{"date":"1894-Jul-01","Ls":30.0},{"date":"1895-Jan-01","Ls":31.2},{"date":"1895-Jul-01","Ls":32.3},{"date":"1896-Jan-01","Ls":33.4},{"date":"1896-Jul-01","Ls":34.5},{"date":"1897-Jan-01","Ls":35.6},{"date":"1897-Jul-01","Ls":36.7},{"date":"1898-Jan-01","Ls":37.8},{"date":"1898-Jul-01","Ls":38.9},{"date":"1899-Jan-01","Ls":40.0},{"date":"1899-Jul-01","Ls":41.1},{"date":"1900-Jan-01","Ls":42.2},{"date":"1900-Jul-01","Ls":43.3},{"date":"1901-Jan-01","Ls":44.4},{"date":"1901-Jul-01","Ls":45.5},{"date":"1902-Jan-01","Ls":46.6},{"date":"1902-Jul-01","Ls":47.7},{"date":"1903-Jan-01","Ls":48.8},{"date":"1903-Jul-01","Ls":49.9},{"date":"1904-Jan-01","Ls":51.0},{"date":"1904-Jul-01","Ls":52.1},{"date":"1905-Jan-01","Ls":53.2},{"date":"1905-Jul-01","Ls":54.3},{"date":"1906-Jan-01","Ls":55.4},{"date":"1906-Jul-01","Ls":56.5},{"date":"1907-Jan-01","Ls":57.6},{"date":"1907-Jul-01","Ls":58.7},{"date":"1908-Jan-01","Ls":59.8},{"date":"1908-Jul-01","Ls":60.9},{"date":"1909-Jan-01","Ls":62.0},{"date":"1909-Jul-01","Ls":63.1},{"date":"1910-Jan-01","Ls":64.2},{"date":"1910-Jul-01","Ls":65.3},{"date":"1911-Jan-01","Ls":66.4},{"date":"1911-Jul-01","Ls":67.5},{"date":"1912-Jan-01","Ls":68.6},{"date":"1912-Jul-01","Ls":69.7},{"date":"1913-Jan-01","Ls":70.8},{"date":"1913-Jul-01","Ls":71.9},{"date":"1914-Jan-01","Ls":73.0},{"date":"1914-Jul-01","Ls":74.1},{"date":"1915-Jan-01","Ls":75.2},{"date":"1915-Jul-01","Ls":76.3},{"date":"1916-Jan-01","Ls":77.4},{"date":"1916-Jul-01","Ls":78.5},{"date":"1917-Jan-01","Ls":79.6},{"date":"1917-Jul-01","Ls":80.7},{"date":"1918-Jan-01","Ls":81.8},{"date":"1918-Jul-01","Ls":82.9},{"date":"1919-Jan-01","Ls":84.0},{"date":"1919-Jul-01","Ls":85.1},{"date":"1920-Jan-01","Ls":86.2},{"date":"1920-Jul-01","Ls":87.2},{"date":"1921-Jan-01","Ls":88.3},{"date":"1921-Jul-01","Ls":89.4},{"date":"1922-Jan-01","Ls":90.5},{"date":"1922-Jul-01","Ls":91.6},{"date":"1923-Jan-01","Ls":92.7},{"date":"1923-Jul-01","Ls":93.8},{"date":"1924-Jan-01","Ls":94.9},{"date":"1924-Jul-01","Ls":96.0},{"date":"1925-Jan-01","Ls":97.1},{"date":"1925-Jul-01","Ls":98.1},{"date":"1926-Jan-01","Ls":99.2},{"date":"1926-Jul-01","Ls":100.3},{"date":"1927-Jan-01","Ls":101.4},{"date":"1927-Jul-01","Ls":102.5},{"date":"1928-Jan-01","Ls":103.6},{"date":"1928-Jul-01","Ls":104.6},{"date":"1929-Jan-01","Ls":105.7},{"date":"1929-Jul-01","Ls":106.8},{"date":"1930-Jan-01","Ls":107.9},{"date":"1930-Jul-01","Ls":109.0},{"date":"1931-Jan-01","Ls":110.1},{"date":"1931-Jul-01","Ls":111.1},{"date":"1932-Jan-01","Ls":112.2},{"date":"1932-Jul-01","Ls":113.3},{"date":"1933-Jan-01","Ls":114.4},{"date":"1933-Jul-01","Ls":115.5},{"date":"1934-Jan-01","Ls":116.6},{"date":"1934-Jul-01","Ls":117.6},{"date":"1935-Jan-01","Ls":118.7},{"date":"1935-Jul-01","Ls":119.8},{"date":"1936-Jan-01","Ls":120.9},{"date":"1936-Jul-01","Ls":122.0},{"date":"1937-Jan-01","Ls":123.1},{"date":"1937-Jul-01","Ls":124.1},{"date":"1938-Jan-01","Ls":125.2},{"date":"1938-Jul-01","Ls":126.3},{"date":"1939-Jan-01","Ls":127.4},{"date":"1939-Jul-01","Ls":128.4},{"date":"1940-Jan-01","Ls":129.5},{"date":"1940-Jul-01","Ls":130.6},{"date":"1941-Jan-01","Ls":131.7},{"date":"1941-Jul-01","Ls":132.7},{"date":"1942-Jan-01","Ls":133.8},{"date":"1942-Jul-01","Ls":134.9},{"date":"1943-Jan-01","Ls":136.0},{"date":"1943-Jul-01","Ls":137.0},{"date":"1944-Jan-01","Ls":138.1},{"date":"1944-Jul-01","Ls":139.2},{"date":"1945-Jan-01","Ls":140.3},{"date":"1945-Jul-01","Ls":141.3},{"date":"1946-Jan-01","Ls":142.4},{"date":"1946-Jul-01","Ls":143.5},{"date":"1947-Jan-01","Ls":144.6},{"date":"1947-Jul-01","Ls":145.7},{"date":"1948-Jan-01","Ls":146.7},{"date":"1948-Jul-01","Ls":147.8},{"date":"1949-Jan-01","Ls":148.9},{"date":"1949-Jul-01","Ls":150.0},{"date":"1950-Jan-01","Ls":151.0},{"date":"1950-Jul-01","Ls":152.1},{"date":"1951-Jan-01","Ls":153.2},{"date":"1951-Jul-01","Ls":154.2},{"date":"1952-Jan-01","Ls":155.3},{"date":"1952-Jul-01","Ls":156.4},{"date":"1953-Jan-01","Ls":157.5},{"date":"1953-Jul-01","Ls":158.5},{"date":"1954-Jan-01","Ls":159.6},{"date":"1954-Jul-01","Ls":160.7},{"date":"1955-Jan-01","Ls":161.7},{"date":"1955-Jul-01","Ls":162.8},{"date":"1956-Jan-01","Ls":163.9},{"date":"1956-Jul-01","Ls":165.0},{"date":"1957-Jan-01","Ls":166.0},{"date":"1957-Jul-01","Ls":167.1},{"date":"1958-Jan-01","Ls":168.2},{"date":"1958-Jul-01","Ls":169.2},{"date":"1959-Jan-01","Ls":170.3},{"date":"1959-Jul-01","Ls":171.4},{"date":"1960-Jan-01","Ls":172.5},{"date":"1960-Jul-01","Ls":173.5},{"date":"1961-Jan-01","Ls":174.6},{"date":"1961-Jul-01","Ls":175.7},{"date":"1962-Jan-01","Ls":176.8},{"date":"1962-Jul-01","Ls":177.8},{"date":"1963-Jan-01","Ls":178.9},{"date":"1963-Jul-01","Ls":179.9},{"date":"1964-Jan-01","Ls":181.0},{"date":"1964-Jul-01","Ls":182.1},{"date":"1965-Jan-01","Ls":183.2},{"date":"1965-Jul-01","Ls":184.2},{"date":"1966-Jan-01","Ls":185.3},{"date":"1966-Jul-01","Ls":186.4},{"date":"1967-Jan-01","Ls":187.4},{"date":"1967-Jul-01","Ls":188.5},{"date":"1968-Jan-01","Ls":189.6},{"date":"1968-Jul-01","Ls":190.6},{"date":"1969-Jan-01","Ls":191.7},{"date":"1969-Jul-01","Ls":192.8},{"date":"1970-Jan-01","Ls":193.9},{"date":"1970-Jul-01","Ls":194.9},{"date":"1971-Jan-01","Ls":196.0},{"date":"1971-Jul-01","Ls":197.1},{"date":"1972-Jan-01","Ls":198.1},{"date":"1972-Jul-01","Ls":199.2},{"date":"1973-Jan-01","Ls":200.3},{"date":"1973-Jul-01","Ls":201.4},{"date":"1974-Jan-01","Ls":202.4},{"date":"1974-Jul-01","Ls":203.5},{"date":"1975-Jan-01","Ls":204.6},{"date":"1975-Jul-01","Ls":205.6},{"date":"1976-Jan-01","Ls":206.7},{"date":"1976-Jul-01","Ls":207.8},{"date":"1977-Jan-01","Ls":208.9},{"date":"1977-Jul-01","Ls":209.9},{"date":"1978-Jan-01","Ls":211.0},{"date":"1978-Jul-01","Ls":212.1},{"date":"1979-Jan-01","Ls":213.1},{"date":"1979-Jul-01","Ls":214.2},{"date":"1980-Jan-01","Ls":215.3},{"date":"1980-Jul-01","Ls":216.4},{"date":"1981-Jan-01","Ls":217.4},{"date":"1981-Jul-01","Ls":218.5},{"date":"1982-Jan-01","Ls":219.6},{"date":"1982-Jul-01","Ls":220.6},{"date":"1983-Jan-01","Ls":221.7},{"date":"1983-Jul-01","Ls":222.8},{"date":"1984-Jan-01","Ls":223.9},{"date":"1984-Jul-01","Ls":224.9},{"date":"1985-Jan-01","Ls":226.0},{"date":"1985-Jul-01","Ls":227.1},{"date":"1986-Jan-01","Ls":228.2},{"date":"1986-Jul-01","Ls":229.3},{"date":"1987-Jan-01","Ls":230.3},{"date":"1987-Jul-01","Ls":231.4},{"date":"1988-Jan-01","Ls":232.5},{"date":"1988-Jul-01","Ls":233.6},{"date":"1989-Jan-01","Ls":234.6},{"date":"1989-Jul-01","Ls":235.7},{"date":"1990-Jan-01","Ls":236.8},{"date":"1990-Jul-01","Ls":237.9},{"date":"1991-Jan-01","Ls":238.9},{"date":"1991-Jul-01","Ls":240.0},{"date":"1992-Jan-01","Ls":241.1},{"date":"1992-Jul-01","Ls":242.2},{"date":"1993-Jan-01","Ls":243.3},{"date":"1993-Jul-01","Ls":244.3},{"date":"1994-Jan-01","Ls":245.4},{"date":"1994-Jul-01","Ls":246.5},{"date":"1995-Jan-01","Ls":247.6},{"date":"1995-Jul-01","Ls":248.7},{"date":"1996-Jan-01","Ls":249.8},{"date":"1996-Jul-01","Ls":250.8},{"date":"1997-Jan-01","Ls":251.9},{"date":"1997-Jul-01","Ls":253.0},{"date":"1998-Jan-01","Ls":254.1},{"date":"1998-Jul-01","Ls":255.2},{"date":"1999-Jan-01","Ls":256.3},{"date":"1999-Jul-01","Ls":257.3},{"date":"2000-Jan-01","Ls":258.4},{"date":"2000-Jul-01","Ls":259.5},{"date":"2001-Jan-01","Ls":260.6},{"date":"2001-Jul-01","Ls":261.7},{"date":"2002-Jan-01","Ls":262.8},{"date":"2002-Jul-01","Ls":263.8},{"date":"2003-Jan-01","Ls":264.9},{"date":"2003-Jul-01","Ls":266.0},{"date":"2004-Jan-01","Ls":267.1},{"date":"2004-Jul-01","Ls":268.2},{"date":"2005-Jan-01","Ls":269.3},{"date":"2005-Jul-01","Ls":270.3},{"date":"2006-Jan-01","Ls":271.4},{"date":"2006-Jul-01","Ls":272.5},{"date":"2007-Jan-01","Ls":273.6},{"date":"2007-Jul-01","Ls":274.7},{"date":"2008-Jan-01","Ls":275.8},{"date":"2008-Jul-01","Ls":276.9},{"date":"2009-Jan-01","Ls":278.0},{"date":"2009-Jul-01","Ls":279.1},{"date":"2010-Jan-01","Ls":280.2},{"date":"2010-Jul-01","Ls":281.3},{"date":"2011-Jan-01","Ls":282.3},{"date":"2011-Jul-01","Ls":283.4},{"date":"2012-Jan-01","Ls":284.5},{"date":"2012-Jul-01","Ls":285.6},{"date":"2013-Jan-01","Ls":286.7},{"date":"2013-Jul-01","Ls":287.8},{"date":"2014-Jan-01","Ls":288.9},{"date":"2014-Jul-01","Ls":290.0},{"date":"2015-Jan-01","Ls":291.1},{"date":"2015-Jul-01","Ls":292.2},{"date":"2016-Jan-01","Ls":293.3},{"date":"2016-Jul-01","Ls":294.4},{"date":"2017-Jan-01","Ls":295.5},{"date":"2017-Jul-01","Ls":296.6},{"date":"2018-Jan-01","Ls":297.7},{"date":"2018-Jul-01","Ls":298.7},{"date":"2019-Jan-01","Ls":299.8},{"date":"2019-Jul-01","Ls":300.9},{"date":"2020-Jan-01","Ls":302.0},{"date":"2020-Jul-01","Ls":303.1},{"date":"2021-Jan-01","Ls":304.2},{"date":"2021-Jul-01","Ls":305.3},{"date":"2022-Jan-01","Ls":306.4},{"date":"2022-Jul-01","Ls":307.5},{"date":"2023-Jan-01","Ls":308.7},{"date":"2023-Jul-01","Ls":309.7},{"date":"2024-Jan-01","Ls":310.9},{"date":"2024-Jul-01","Ls":312.0},{"date":"2025-Jan-01","Ls":313.1},{"date":"2025-Jul-01","Ls":314.2},{"date":"2026-Jan-01","Ls":315.3},{"date":"2026-Jul-01","Ls":316.4},{"date":"2027-Jan-01","Ls":317.5},{"date":"2027-Jul-01","Ls":318.6},{"date":"2028-Jan-01","Ls":319.7},{"date":"2028-Jul-01","Ls":320.8},{"date":"2029-Jan-01","Ls":321.9},{"date":"2029-Jul-01","Ls":323.0},{"date":"2030-Jan-01","Ls":324.1},{"date":"2030-Jul-01","Ls":325.2},{"date":"2031-Jan-01","Ls":326.3},{"date":"2031-Jul-01","Ls":327.4},{"date":"2032-Jan-01","Ls":328.5},{"date":"2032-Jul-01","Ls":329.6},{"date":"2033-Jan-01","Ls":330.7},{"date":"2033-Jul-01","Ls":331.8},{"date":"2034-Jan-01","Ls":332.9},{"date":"2034-Jul-01","Ls":334.0},{"date":"2035-Jan-01","Ls":335.1},{"date":"2035-Jul-01","Ls":336.2},{"date":"2036-Jan-01","Ls":337.3},{"date":"2036-Jul-01","Ls":338.4},{"date":"2037-Jan-01","Ls":339.6},{"date":"2037-Jul-01","Ls":340.6},{"date":"2038-Jan-01","Ls":341.8},{"date":"2038-Jul-01","Ls":342.9},{"date":"2039-Jan-01","Ls":344.0},{"date":"2039-Jul-01","Ls":345.1},{"date":"2040-Jan-01","Ls":346.2},{"date":"2040-Jul-01","Ls":347.3},{"date":"2041-Jan-01","Ls":348.4},{"date":"2041-Jul-01","Ls":349.5},{"date":"2042-Jan-01","Ls":350.6},{"date":"2042-Jul-01","Ls":351.7},{"date":"2043-Jan-01","Ls":352.8},{"date":"2043-Jul-01","Ls":353.9},{"date":"2044-Jan-01","Ls":355.0},{"date":"2044-Jul-01","Ls":356.1},{"date":"2045-Jan-01","Ls":357.2},{"date":"2045-Jul-01","Ls":358.3},{"date":"2046-Jan-01","Ls":359.4},{"date":"2046-Jul-01","Ls":0.5},{"date":"2047-Jan-01","Ls":1.6},{"date":"2047-Jul-01","Ls":2.7},{"date":"2048-Jan-01","Ls":3.9},{"date":"2048-Jul-01","Ls":5.0},{"date":"2049-Jan-01","Ls":6.1},{"date":"2049-Jul-01","Ls":7.2},{"date":"2050-Jan-01","Ls":8.3},{"date":"2050-Jul-01","Ls":9.4},{"date":"2051-Jan-01","Ls":10.5},{"date":"2051-Jul-01","Ls":11.6},{"date":"2052-Jan-01","Ls":12.7},{"date":"2052-Jul-01","Ls":13.8},{"date":"2053-Jan-01","Ls":14.9},{"date":"2053-Jul-01","Ls":16.0},{"date":"2054-Jan-01","Ls":17.1},{"date":"2054-Jul-01","Ls":18.2},{"date":"2055-Jan-01","Ls":19.3},{"date":"2055-Jul-01","Ls":20.4},{"date":"2056-Jan-01","Ls":21.5},{"date":"2056-Jul-01","Ls":22.7},{"date":"2057-Jan-01","Ls":23.8},{"date":"2057-Jul-01","Ls":24.9},{"date":"2058-Jan-01","Ls":26.0},{"date":"2058-Jul-01","Ls":27.1},{"date":"2059-Jan-01","Ls":28.2},{"date":"2059-Jul-01","Ls":29.3},{"date":"2060-Jan-01","Ls":30.4},{"date":"2060-Jul-01","Ls":31.5},{"date":"2061-Jan-01","Ls":32.6},{"date":"2061-Jul-01","Ls":33.7},{"date":"2062-Jan-01","Ls":34.8},{"date":"2062-Jul-01","Ls":35.9},{"date":"2063-Jan-01","Ls":37.0},{"date":"2063-Jul-01","Ls":38.1},{"date":"2064-Jan-01","Ls":39.2},{"date":"2064-Jul-01","Ls":40.3},{"date":"2065-Jan-01","Ls":41.4},{"date":"2065-Jul-01","Ls":42.5},{"date":"2066-Jan-01","Ls":43.6},{"date":"2066-Jul-01","Ls":44.7},{"date":"2067-Jan-01","Ls":45.8},{"date":"2067-Jul-01","Ls":46.9},{"date":"2068-Jan-01","Ls":48.0},{"date":"2068-Jul-01","Ls":49.1},{"date":"2069-Jan-01","Ls":50.2},{"date":"2069-Jul-01","Ls":51.3},{"date":"2070-Jan-01","Ls":52.4},{"date":"2070-Jul-01","Ls":53.5},{"date":"2071-Jan-01","Ls":54.6},{"date":"2071-Jul-01","Ls":55.7},{"date":"2072-Jan-01","Ls":56.8},{"date":"2072-Jul-01","Ls":57.9},{"date":"2073-Jan-01","Ls":59.0},{"date":"2073-Jul-01","Ls":60.1},{"date":"2074-Jan-01","Ls":61.2},{"date":"2074-Jul-01","Ls":62.3},{"date":"2075-Jan-01","Ls":63.4},{"date":"2075-Jul-01","Ls":64.5},{"date":"2076-Jan-01","Ls":65.6},{"date":"2076-Jul-01","Ls":66.7},{"date":"2077-Jan-01","Ls":67.8},{"date":"2077-Jul-01","Ls":68.9},{"date":"2078-Jan-01","Ls":70.0},{"date":"2078-Jul-01","Ls":71.1},{"date":"2079-Jan-01","Ls":72.2},{"date":"2079-Jul-01","Ls":73.2},{"date":"2080-Jan-01","Ls":74.3},{"date":"2080-Jul-01","Ls":75.4},{"date":"2081-Jan-01","Ls":76.5},{"date":"2081-Jul-01","Ls":77.6},{"date":"2082-Jan-01","Ls":78.7},{"date":"2082-Jul-01","Ls":79.8},{"date":"2083-Jan-01","Ls":80.9},{"date":"2083-Jul-01","Ls":82.0},{"date":"2084-Jan-01","Ls":83.0},{"date":"2084-Jul-01","Ls":84.1},{"date":"2085-Jan-01","Ls":85.2},{"date":"2085-Jul-01","Ls":86.3},{"date":"2086-Jan-01","Ls":87.4},{"date":"2086-Jul-01","Ls":88.5},{"date":"2087-Jan-01","Ls":89.6},{"date":"2087-Jul-01","Ls":90.7},{"date":"2088-Jan-01","Ls":91.8},{"date":"2088-Jul-01","Ls":92.8},{"date":"2089-Jan-01","Ls":93.9},{"date":"2089-Jul-01","Ls":95.0},{"date":"2090-Jan-01","Ls":96.1},{"date":"2090-Jul-01","Ls":97.2},{"date":"2091-Jan-01","Ls":98.3},{"date":"2091-Jul-01","Ls":99.3},{"date":"2092-Jan-01","Ls":100.4},{"date":"2092-Jul-01","Ls":101.5},{"date":"2093-Jan-01","Ls":102.6},{"date":"2093-Jul-01","Ls":103.7},{"date":"2094-Jan-01","Ls":104.8},{"date":"2094-Jul-01","Ls":105.9},{"date":"2095-Jan-01","Ls":106.9},{"date":"2095-Jul-01","Ls":108.0},{"date":"2096-Jan-01","Ls":109.1},{"date":"2096-Jul-01","Ls":110.2},{"date":"2097-Jan-01","Ls":111.3},{"date":"2097-Jul-01","Ls":112.3},{"date":"2098-Jan-01","Ls":113.4},{"date":"2098-Jul-01","Ls":114.5},{"date":"2099-Jan-01","Ls":115.6},{"date":"2099-Jul-01","Ls":116.6},{"date":"2100-Jan-01","Ls":117.7},{"date":"2100-Jul-01","Ls":118.8},{"date":"2101-Jan-01","Ls":119.9},{"date":"2101-Jul-01","Ls":121.0},{"date":"2102-Jan-01","Ls":122.1},{"date":"2102-Jul-01","Ls":123.1},{"date":"2103-Jan-01","Ls":124.2},{"date":"2103-Jul-01","Ls":125.3},{"date":"2104-Jan-01","Ls":126.4},{"date":"2104-Jul-01","Ls":127.4},{"date":"2105-Jan-01","Ls":128.5},{"date":"2105-Jul-01","Ls":129.6},{"date":"2106-Jan-01","Ls":130.7},{"date":"2106-Jul-01","Ls":131.7},{"date":"2107-Jan-01","Ls":132.8},{"date":"2107-Jul-01","Ls":133.9},{"date":"2108-Jan-01","Ls":135.0},{"date":"2108-Jul-01","Ls":136.0},{"date":"2109-Jan-01","Ls":137.1},{"date":"2109-Jul-01","Ls":138.2},{"date":"2110-Jan-01","Ls":139.3},{"date":"2110-Jul-01","Ls":140.3},{"date":"2111-Jan-01","Ls":141.4},{"date":"2111-Jul-01","Ls":142.5},{"date":"2112-Jan-01","Ls":143.5},{"date":"2112-Jul-01","Ls":144.6},{"date":"2113-Jan-01","Ls":145.7},{"date":"2113-Jul-01","Ls":146.8},{"date":"2114-Jan-01","Ls":147.8},{"date":"2114-Jul-01","Ls":148.9},{"date":"2115-Jan-01","Ls":150.0},{"date":"2115-Jul-01","Ls":151.0},{"date":"2116-Jan-01","Ls":152.1},{"date":"2116-Jul-01","Ls":153.2},{"date":"2117-Jan-01","Ls":154.3},{"date":"2117-Jul-01","Ls":155.3},{"date":"2118-Jan-01","Ls":156.4},{"date":"2118-Jul-01","Ls":157.5},{"date":"2119-Jan-01","Ls":158.5},{"date":"2119-Jul-01","Ls":159.6},{"date":"2120-Jan-01","Ls":160.7},{"date":"2120-Jul-01","Ls":161.7},{"date":"2121-Jan-01","Ls":162.8},{"date":"2121-Jul-01","Ls":163.9},{"date":"2122-Jan-01","Ls":165.0},{"date":"2122-Jul-01","Ls":166.0},{"date":"2123-Jan-01","Ls":167.1},{"date":"2123-Jul-01","Ls":168.2},{"date":"2124-Jan-01","Ls":169.2},{"date":"2124-Jul-01","Ls":170.3},{"date":"2125-Jan-01","Ls":171.4},{"date":"2125-Jul-01","Ls":172.5},{"date":"2126-Jan-01","Ls":173.5},{"date":"2126-Jul-01","Ls":174.6},{"date":"2127-Jan-01","Ls":175.7},{"date":"2127-Jul-01","Ls":176.7},{"date":"2128-Jan-01","Ls":177.8},{"date":"2128-Jul-01","Ls":178.9},{"date":"2129-Jan-01","Ls":180.0},{"date":"2129-Jul-01","Ls":181.0},{"date":"2130-Jan-01","Ls":182.1},{"date":"2130-Jul-01","Ls":183.1},{"date":"2131-Jan-01","Ls":184.2},{"date":"2131-Jul-01","Ls":185.3},{"date":"2132-Jan-01","Ls":186.4},{"date":"2132-Jul-01","Ls":187.4},{"date":"2133-Jan-01","Ls":188.5},{"date":"2133-Jul-01","Ls":189.6},{"date":"2134-Jan-01","Ls":190.6},{"date":"2134-Jul-01","Ls":191.7},{"date":"2135-Jan-01","Ls":192.8},{"date":"2135-Jul-01","Ls":193.8},{"date":"2136-Jan-01","Ls":194.9},{"date":"2136-Jul-01","Ls":196.0},{"date":"2137-Jan-01","Ls":197.1},{"date":"2137-Jul-01","Ls":198.1},{"date":"2138-Jan-01","Ls":199.2},{"date":"2138-Jul-01","Ls":200.3},{"date":"2139-Jan-01","Ls":201.4},{"date":"2139-Jul-01","Ls":202.4},{"date":"2140-Jan-01","Ls":203.5},{"date":"2140-Jul-01","Ls":204.6},{"date":"2141-Jan-01","Ls":205.7},{"date":"2141-Jul-01","Ls":206.7},{"date":"2142-Jan-01","Ls":207.8},{"date":"2142-Jul-01","Ls":208.9},{"date":"2143-Jan-01","Ls":209.9},{"date":"2143-Jul-01","Ls":211.0},{"date":"2144-Jan-01","Ls":212.1},{"date":"2144-Jul-01","Ls":213.2},{"date":"2145-Jan-01","Ls":214.2},{"date":"2145-Jul-01","Ls":215.3},{"date":"2146-Jan-01","Ls":216.4},{"date":"2146-Jul-01","Ls":217.4},{"date":"2147-Jan-01","Ls":218.5},{"date":"2147-Jul-01","Ls":219.6},{"date":"2148-Jan-01","Ls":220.7},{"date":"2148-Jul-01","Ls":221.8},{"date":"2149-Jan-01","Ls":222.8},{"date":"2149-Jul-01","Ls":223.9},{"date":"2150-Jan-01","Ls":225.0},{"date":"2150-Jul-01","Ls":226.1},{"date":"2151-Jan-01","Ls":227.1},{"date":"2151-Jul-01","Ls":228.2},{"date":"2152-Jan-01","Ls":229.3},{"date":"2152-Jul-01","Ls":230.4},{"date":"2153-Jan-01","Ls":231.5},{"date":"2153-Jul-01","Ls":232.5},{"date":"2154-Jan-01","Ls":233.6},{"date":"2154-Jul-01","Ls":234.7},{"date":"2155-Jan-01","Ls":235.8},{"date":"2155-Jul-01","Ls":236.8},{"date":"2156-Jan-01","Ls":237.9},{"date":"2156-Jul-01","Ls":239.0},{"date":"2157-Jan-01","Ls":240.1},{"date":"2157-Jul-01","Ls":241.2},{"date":"2158-Jan-01","Ls":242.2},{"date":"2158-Jul-01","Ls":243.3},{"date":"2159-Jan-01","Ls":244.4},{"date":"2159-Jul-01","Ls":245.5},{"date":"2160-Jan-01","Ls":246.6},{"date":"2160-Jul-01","Ls":247.6},{"date":"2161-Jan-01","Ls":248.7},{"date":"2161-Jul-01","Ls":249.8},{"date":"2162-Jan-01","Ls":250.9},{"date":"2162-Jul-01","Ls":252.0},{"date":"2163-Jan-01","Ls":253.1},{"date":"2163-Jul-01","Ls":254.1},{"date":"2164-Jan-01","Ls":255.3},{"date":"2164-Jul-01","Ls":256.3},{"date":"2165-Jan-01","Ls":257.4},{"date":"2165-Jul-01","Ls":258.5},{"date":"2166-Jan-01","Ls":259.6},{"date":"2166-Jul-01","Ls":260.7},{"date":"2167-Jan-01","Ls":261.8},{"date":"2167-Jul-01","Ls":262.9},{"date":"2168-Jan-01","Ls":264.0},{"date":"2168-Jul-01","Ls":265.0},{"date":"2169-Jan-01","Ls":266.1},{"date":"2169-Jul-01","Ls":267.2},{"date":"2170-Jan-01","Ls":268.3},{"date":"2170-Jul-01","Ls":269.4},{"date":"2171-Jan-01","Ls":270.5},{"date":"2171-Jul-01","Ls":271.6},{"date":"2172-Jan-01","Ls":272.7},{"date":"2172-Jul-01","Ls":273.8},{"date":"2173-Jan-01","Ls":274.9},{"date":"2173-Jul-01","Ls":275.9},{"date":"2174-Jan-01","Ls":277.1},{"date":"2174-Jul-01","Ls":278.1},{"date":"2175-Jan-01","Ls":279.2},{"date":"2175-Jul-01","Ls":280.3},{"date":"2176-Jan-01","Ls":281.4},{"date":"2176-Jul-01","Ls":282.5},{"date":"2177-Jan-01","Ls":283.6},{"date":"2177-Jul-01","Ls":284.7},{"date":"2178-Jan-01","Ls":285.8},{"date":"2178-Jul-01","Ls":286.9},{"date":"2179-Jan-01","Ls":288.0},{"date":"2179-Jul-01","Ls":289.1},{"date":"2180-Jan-01","Ls":290.2},{"date":"2180-Jul-01","Ls":291.3},{"date":"2181-Jan-01","Ls":292.4},{"date":"2181-Jul-01","Ls":293.5},{"date":"2182-Jan-01","Ls":294.6},{"date":"2182-Jul-01","Ls":295.7},{"date":"2183-Jan-01","Ls":296.8},{"date":"2183-Jul-01","Ls":297.9},{"date":"2184-Jan-01","Ls":299.0},{"date":"2184-Jul-01","Ls":300.1},{"date":"2185-Jan-01","Ls":301.2},{"date":"2185-Jul-01","Ls":302.3},{"date":"2186-Jan-01","Ls":303.4},{"date":"2186-Jul-01","Ls":304.5},{"date":"2187-Jan-01","Ls":305.6},{"date":"2187-Jul-01","Ls":306.7},{"date":"2188-Jan-01","Ls":307.8},{"date":"2188-Jul-01","Ls":308.9},{"date":"2189-Jan-01","Ls":310.0},{"date":"2189-Jul-01","Ls":311.1},{"date":"2190-Jan-01","Ls":312.2},{"date":"2190-Jul-01","Ls":313.3},{"date":"2191-Jan-01","Ls":314.5},{"date":"2191-Jul-01","Ls":315.5},{"date":"2192-Jan-01","Ls":316.7},{"date":"2192-Jul-01","Ls":317.8},{"date":"2193-Jan-01","Ls":318.9},{"date":"2193-Jul-01","Ls":320.0},{"date":"2194-Jan-01","Ls":321.1},{"date":"2194-Jul-01","Ls":322.2},{"date":"2195-Jan-01","Ls":323.3},{"date":"2195-Jul-01","Ls":324.4},{"date":"2196-Jan-01","Ls":325.5},{"date":"2196-Jul-01","Ls":326.6},{"date":"2197-Jan-01","Ls":327.7},{"date":"2197-Jul-01","Ls":328.8},{"date":"2198-Jan-01","Ls":329.9},{"date":"2198-Jul-01","Ls":331.0},{"date":"2199-Jan-01","Ls":332.1},{"date":"2199-Jul-01","Ls":333.2},{"date":"2200-Jan-01","Ls":334.4}]}